scuts/__init__.py
scuts/__main__.py
scuts/img_detection_utils.py
scuts/img_functions.py
scuts/scraping.py
scuts/utils.py
scuts/ressources/faster_rcnn_resnet101.config
scuts/ressources/jquery-1.9.1.min.js
scuts-2019.1.9.1.dist-info/LICENSE
scuts-2019.1.9.1.dist-info/METADATA
scuts-2019.1.9.1.dist-info/WHEEL
scuts-2019.1.9.1.dist-info/top_level.txt
scuts-2019.1.9.1.dist-info/RECORD
