Metadata-Version: 2.1
Name: scuts
Version: 2019.1.9.1
Summary: Python Standard Shortcuts
Home-page: UNKNOWN
Author: Arthur RENAUD
Author-email: arthur.b.renaud@gmail.com
License: UNKNOWN
Platform: UNKNOWN
Classifier: Programming Language :: Python
Classifier: Development Status :: 1 - Planning
Classifier: License :: OSI Approved
Classifier: Natural Language :: French
Classifier: Operating System :: OS Independent
Classifier: Programming Language :: Python :: 3.6
Classifier: Topic :: Communications
Requires-Python: >=3.5
